ciscoglass/__init__.py
ciscoglass/__main__.py
ciscoglass/app.py
ciscoglass/samples.py
ciscoglass-0.1.5.dist-info/METADATA
ciscoglass-0.1.5.dist-info/WHEEL
ciscoglass-0.1.5.dist-info/top_level.txt
ciscoglass-0.1.5.dist-info/RECORD
