Metadata-Version: 2.1
Name: ciscoglass
Version: 0.1.5
Summary: Wrapper/SDK for Cisco Glass Apps
Home-page: https://wwwin-github.cisco.com/ciscoglass/python-sdk.git
Author: Adyanth H
Author-email: adyah@cisco.com
License: UNKNOWN
Platform: UNKNOWN
Classifier: Operating System :: POSIX :: Linux
Classifier: Programming Language :: Python :: 3.8
Requires-Dist: requests
Requires-Dist: click
